{
  "updated_at": "2026-06-25T08:46:49.089027+09:00",
  "article_date": "2026-06-24",
  "sources": [
    "irbank",
    "kabutan",
    "kabupro"
  ],
  "source_counts": {
    "irbank": 4,
    "kabutan": 6,
    "kabupro": 7
  },
  "source_dates": {
    "irbank": "2026-06-24",
    "kabutan": "06/24",
    "kabupro": "2026-06-24"
  },
  "groups": [
    {
      "category": "増配・配当修正",
      "display": "増配・配当修正",
      "priority": 40,
      "zone": "positive",
      "items": [
        {
          "code": "3010",
          "name": "ポラリスＨＤ",
          "time": "16:00",
          "category": "増配・配当修正",
          "narrative": "今期配当を5円増額修正",
          "narrative_source": "kabutan",
          "metrics": null,
          "chips": [],
          "sources": [
            "kabutan",
            "kabupro"
          ],
          "primary_source": "kabutan",
          "url": "https://kabutan.jp/news/?&b=k202606240006"
        },
        {
          "code": "550A",
          "name": "ソフトテック",
          "time": "15:30",
          "category": "増配・配当修正",
          "narrative": "今期配当を5円増額修正",
          "narrative_source": "kabutan",
          "metrics": null,
          "chips": [],
          "sources": [
            "kabutan"
          ],
          "primary_source": "kabutan",
          "url": "https://kabutan.jp/news/?&b=k202606240003"
        }
      ]
    },
    {
      "category": "本決算・四半期決算",
      "display": "決算発表",
      "priority": 60,
      "zone": "decision",
      "items": [
        {
          "code": "9976",
          "name": "セキチュー",
          "time": "16:00",
          "category": "本決算・四半期決算",
          "narrative": "3-5月期(1Q)経常は23％増益で着地",
          "narrative_source": "kabutan",
          "metrics": {
            "period": "2026/05 4ヶ月",
            "type": "実績",
            "sales": "80.8億 +3.3%",
            "op": "3.71億 +24.3%",
            "ord": "3.63億 +22.6%",
            "net": "2.53億 +20.7%"
          },
          "chips": [
            {
              "label": "売上",
              "value": "+3.3%",
              "direction": "up",
              "strength": "normal",
              "pct": 3.3
            },
            {
              "label": "営業益",
              "value": "+24.3%",
              "direction": "up",
              "strength": "normal",
              "pct": 24.3
            },
            {
              "label": "経常",
              "value": "+22.6%",
              "direction": "up",
              "strength": "normal",
              "pct": 22.6
            },
            {
              "label": "純益",
              "value": "+20.7%",
              "direction": "up",
              "strength": "normal",
              "pct": 20.7
            }
          ],
          "sources": [
            "irbank",
            "kabutan",
            "kabupro"
          ],
          "primary_source": "irbank",
          "url": "https://irbank.net/9976"
        },
        {
          "code": "2742",
          "name": "ハローズ",
          "time": "15:30",
          "category": "本決算・四半期決算",
          "narrative": "3-5月期(1Q)経常は10％減益で着地",
          "narrative_source": "kabutan",
          "metrics": {
            "period": "2026/05 3ヶ月",
            "type": "実績",
            "sales": "579億 +7.2%",
            "op": "27.3億 -10.5%",
            "ord": "27.5億 -10.2%",
            "net": "19.8億 -7.2%"
          },
          "chips": [
            {
              "label": "売上",
              "value": "+7.2%",
              "direction": "up",
              "strength": "normal",
              "pct": 7.2
            },
            {
              "label": "営業益",
              "value": "-10.5%",
              "direction": "down",
              "strength": "normal",
              "pct": 10.5
            },
            {
              "label": "経常",
              "value": "-10.2%",
              "direction": "down",
              "strength": "normal",
              "pct": 10.2
            },
            {
              "label": "純益",
              "value": "-7.2%",
              "direction": "down",
              "strength": "normal",
              "pct": 7.2
            }
          ],
          "sources": [
            "irbank",
            "kabutan",
            "kabupro"
          ],
          "primary_source": "irbank",
          "url": "https://irbank.net/2742"
        },
        {
          "code": "7227",
          "name": "アスカ",
          "time": "15:30",
          "category": "本決算・四半期決算",
          "narrative": "上期経常は32％増益で上振れ着地",
          "narrative_source": "kabutan",
          "metrics": {
            "period": "2026/05 6ヶ月",
            "type": "実績",
            "sales": "235億 +1.7%",
            "op": "12.4億 +33.3%",
            "ord": "13.2億 +32.2%",
            "net": "9.6億 +41%"
          },
          "chips": [
            {
              "label": "売上",
              "value": "+1.7%",
              "direction": "up",
              "strength": "normal",
              "pct": 1.7
            },
            {
              "label": "営業益",
              "value": "+33.3%",
              "direction": "up",
              "strength": "strong",
              "pct": 33.3
            },
            {
              "label": "経常",
              "value": "+32.2%",
              "direction": "up",
              "strength": "strong",
              "pct": 32.2
            },
            {
              "label": "純益",
              "value": "+41%",
              "direction": "up",
              "strength": "strong",
              "pct": 41.0
            }
          ],
          "sources": [
            "irbank",
            "kabutan",
            "kabupro"
          ],
          "primary_source": "irbank",
          "url": "https://irbank.net/7227"
        },
        {
          "code": "6484",
          "name": "ＫＶＫ",
          "time": "15:30",
          "category": "本決算・四半期決算",
          "narrative": "2026年３月期　決算説明資料",
          "narrative_source": "kabupro",
          "metrics": null,
          "chips": [],
          "sources": [
            "kabupro"
          ],
          "primary_source": "kabupro",
          "url": "http://ke.kabupro.jp/tsp/20260624/140120260624578082.pdf"
        }
      ]
    },
    {
      "category": "減配",
      "display": "減配",
      "priority": 85,
      "zone": "negative",
      "items": [
        {
          "code": "9193",
          "name": "東京汽",
          "time": "15:00",
          "category": "減配",
          "narrative": "非開示だった今期経常は赤字転落、未定だった配当は30円実施",
          "narrative_source": "kabutan",
          "metrics": {
            "period": "2026/09 6ヶ月",
            "type": "修正",
            "sales": "63億",
            "op": "-3.14億",
            "ord": "-1.75億",
            "net": "-0.11億"
          },
          "chips": [],
          "sources": [
            "irbank",
            "kabutan",
            "kabupro"
          ],
          "primary_source": "kabutan",
          "url": "https://irbank.net/9193"
        }
      ]
    },
    {
      "category": "その他開示",
      "display": "その他開示",
      "priority": 99,
      "zone": "other",
      "items": [
        {
          "code": "3121",
          "name": "マーチャント・バンカーズ",
          "time": "12:00",
          "category": "その他開示",
          "narrative": "CN Innovations Ho …",
          "narrative_source": "kabupro",
          "metrics": null,
          "chips": [],
          "sources": [
            "kabupro"
          ],
          "primary_source": "kabupro",
          "url": "http://ke.kabupro.jp/tsp/20260624/140120260624577969.pdf"
        }
      ]
    }
  ],
  "total": 8
}