{
  "items": [
    {
      "title": "NY株式：NYダウは159.95ドル高、イラン合意への不透明感を警戒",
      "url": "https://kabutan.jp/news/marketnews/?&b=n202605190078",
      "date": "05/19 06:41",
      "source": "kabutan",
      "source_label": "株探"
    },
    {
      "title": "本日注目の【自社株買い】銘柄　(18日大引け後 発表分)",
      "url": "https://kabutan.jp/news/marketnews/?&b=n202605190077",
      "date": "05/19 06:40",
      "source": "kabutan",
      "source_label": "株探"
    },
    {
      "title": "今日の注目スケジュール：GDP速報値、英失業率、欧ユーロ圏貿易収支など",
      "url": "https://kabutan.jp/news/marketnews/?&b=n202605190076",
      "date": "05/19 06:30",
      "source": "kabutan",
      "source_label": "株探"
    },
    {
      "title": "本日注目の【株主優待】情報 (18日引け後 発表分)",
      "url": "https://kabutan.jp/news/marketnews/?&b=n202605190075",
      "date": "05/19 06:30",
      "source": "kabutan",
      "source_label": "株探"
    },
    {
      "title": "本日の経済スケジュール ─ ★1-3月期GDPに注目",
      "url": "https://kabutan.jp/news/marketnews/?&b=n202605190074",
      "date": "05/19 06:20",
      "source": "kabutan",
      "source_label": "株探"
    },
    {
      "title": "NY為替：米イラン情勢を巡る懸念でドルは乱高下、原油相場に連動",
      "url": "https://kabutan.jp/news/marketnews/?&b=n202605190072",
      "date": "05/19 06:10",
      "source": "kabutan",
      "source_label": "株探"
    },
    {
      "title": "本日注目の【東証スタンダードに市場変更】銘柄　(18日大引け後 発表分)",
      "url": "https://kabutan.jp/news/marketnews/?&b=n202605190071",
      "date": "05/19 06:10",
      "source": "kabutan",
      "source_label": "株探"
    },
    {
      "title": "日経225先物：19日夜間取引終値＝750円高、6万1410円",
      "url": "https://kabutan.jp/news/marketnews/?&b=n202605190069",
      "date": "05/19 06:03",
      "source": "kabutan",
      "source_label": "株探"
    }
  ],
  "updated_at": "2026-05-19T06:46:55.552390+09:00"
}