{
  "updated_at": "2026-07-06T11:01:57.614275+00:00",
  "jp_count": 0,
  "us_count": 20,
  "jp_stocks": [],
  "us_stocks": [
    {
      "symbol": "BKNG",
      "price": 184.56,
      "prev_close": 182.64,
      "change": 1.92,
      "change_pct": 1.05,
      "volume_today": 14188400,
      "volume_yesterday": 7100800,
      "volume_ratio": 99.8,
      "name": "",
      "sector": "",
      "sector_en": "",
      "industry": "",
      "industry_ja": "",
      "description": null,
      "description_ja": "",
      "website": null,
      "chart": null
    },
    {
      "symbol": "FSLR",
      "price": 224.57,
      "prev_close": 232.08,
      "change": -7.51,
      "change_pct": -3.24,
      "volume_today": 2596900,
      "volume_yesterday": 1417500,
      "volume_ratio": 83.2,
      "name": "",
      "sector": "",
      "sector_en": "",
      "industry": "",
      "industry_ja": "",
      "description": null,
      "description_ja": "",
      "website": null,
      "chart": null
    },
    {
      "symbol": "Q",
      "price": 141.75,
      "prev_close": 153.37,
      "change": -11.62,
      "change_pct": -7.58,
      "volume_today": 2817800,
      "volume_yesterday": 1576100,
      "volume_ratio": 78.8,
      "name": "",
      "sector": "",
      "sector_en": "",
      "industry": "",
      "industry_ja": "",
      "description": null,
      "description_ja": "",
      "website": null,
      "chart": null
    },
    {
      "symbol": "AEP",
      "price": 138.51,
      "prev_close": 135.05,
      "change": 3.46,
      "change_pct": 2.56,
      "volume_today": 8802800,
      "volume_yesterday": 4974900,
      "volume_ratio": 76.9,
      "name": "",
      "sector": "",
      "sector_en": "",
      "industry": "",
      "industry_ja": "",
      "description": null,
      "description_ja": "",
      "website": null,
      "chart": null
    },
    {
      "symbol": "MCD",
      "price": 280.63,
      "prev_close": 269.43,
      "change": 11.2,
      "change_pct": 4.16,
      "volume_today": 6871800,
      "volume_yesterday": 3902100,
      "volume_ratio": 76.1,
      "name": "",
      "sector": "",
      "sector_en": "",
      "industry": "",
      "industry_ja": "",
      "description": null,
      "description_ja": "",
      "website": null,
      "chart": null
    },
    {
      "symbol": "AES",
      "price": 14.58,
      "prev_close": 14.64,
      "change": -0.06,
      "change_pct": -0.41,
      "volume_today": 15086300,
      "volume_yesterday": 8637300,
      "volume_ratio": 74.7,
      "name": "",
      "sector": "",
      "sector_en": "",
      "industry": "",
      "industry_ja": "",
      "description": null,
      "description_ja": "",
      "website": null,
      "chart": null
    },
    {
      "symbol": "EME",
      "price": 774.66,
      "prev_close": 804.33,
      "change": -29.67,
      "change_pct": -3.69,
      "volume_today": 569600,
      "volume_yesterday": 342400,
      "volume_ratio": 66.4,
      "name": "",
      "sector": "",
      "sector_en": "",
      "industry": "",
      "industry_ja": "",
      "description": null,
      "description_ja": "",
      "website": null,
      "chart": null
    },
    {
      "symbol": "ISRG",
      "price": 426.01,
      "prev_close": 402.38,
      "change": 23.63,
      "change_pct": 5.87,
      "volume_today": 3139900,
      "volume_yesterday": 1939300,
      "volume_ratio": 61.9,
      "name": "",
      "sector": "",
      "sector_en": "",
      "industry": "",
      "industry_ja": "",
      "description": null,
      "description_ja": "",
      "website": null,
      "chart": null
    },
    {
      "symbol": "COHR",
      "price": 333.36,
      "prev_close": 368.65,
      "change": -35.29,
      "change_pct": -9.57,
      "volume_today": 6965900,
      "volume_yesterday": 4316200,
      "volume_ratio": 61.4,
      "name": "",
      "sector": "",
      "sector_en": "",
      "industry": "",
      "industry_ja": "",
      "description": null,
      "description_ja": "",
      "website": null,
      "chart": null
    },
    {
      "symbol": "PSA",
      "price": 329.64,
      "prev_close": 323.04,
      "change": 6.6,
      "change_pct": 2.04,
      "volume_today": 963400,
      "volume_yesterday": 613000,
      "volume_ratio": 57.2,
      "name": "",
      "sector": "",
      "sector_en": "",
      "industry": "",
      "industry_ja": "",
      "description": null,
      "description_ja": "",
      "website": null,
      "chart": null
    },
    {
      "symbol": "CARR",
      "price": 70.07,
      "prev_close": 72.07,
      "change": -2.0,
      "change_pct": -2.78,
      "volume_today": 6157300,
      "volume_yesterday": 3941400,
      "volume_ratio": 56.2,
      "name": "",
      "sector": "",
      "sector_en": "",
      "industry": "",
      "industry_ja": "",
      "description": null,
      "description_ja": "",
      "website": null,
      "chart": null
    },
    {
      "symbol": "KEYS",
      "price": 313.86,
      "prev_close": 335.6,
      "change": -21.74,
      "change_pct": -6.48,
      "volume_today": 1994700,
      "volume_yesterday": 1318200,
      "volume_ratio": 51.3,
      "name": "",
      "sector": "",
      "sector_en": "",
      "industry": "",
      "industry_ja": "",
      "description": null,
      "description_ja": "",
      "website": null,
      "chart": null
    },
    {
      "symbol": "FTV",
      "price": 62.65,
      "prev_close": 61.8,
      "change": 0.85,
      "change_pct": 1.38,
      "volume_today": 3354700,
      "volume_yesterday": 2231200,
      "volume_ratio": 50.4,
      "name": "",
      "sector": "",
      "sector_en": "",
      "industry": "",
      "industry_ja": "",
      "description": null,
      "description_ja": "",
      "website": null,
      "chart": null
    },
    {
      "symbol": "CAH",
      "price": 238.94,
      "prev_close": 237.72,
      "change": 1.22,
      "change_pct": 0.51,
      "volume_today": 2039100,
      "volume_yesterday": 1369700,
      "volume_ratio": 48.9,
      "name": "",
      "sector": "",
      "sector_en": "",
      "industry": "",
      "industry_ja": "",
      "description": null,
      "description_ja": "",
      "website": null,
      "chart": null
    },
    {
      "symbol": "UHS",
      "price": 158.33,
      "prev_close": 150.58,
      "change": 7.75,
      "change_pct": 5.15,
      "volume_today": 1311100,
      "volume_yesterday": 883000,
      "volume_ratio": 48.5,
      "name": "",
      "sector": "",
      "sector_en": "",
      "industry": "",
      "industry_ja": "",
      "description": null,
      "description_ja": "",
      "website": null,
      "chart": null
    },
    {
      "symbol": "ORLY",
      "price": 90.25,
      "prev_close": 92.69,
      "change": -2.44,
      "change_pct": -2.63,
      "volume_today": 12890900,
      "volume_yesterday": 8694100,
      "volume_ratio": 48.3,
      "name": "",
      "sector": "",
      "sector_en": "",
      "industry": "",
      "industry_ja": "",
      "description": null,
      "description_ja": "",
      "website": null,
      "chart": null
    },
    {
      "symbol": "FIX",
      "price": 1741.3,
      "prev_close": 1865.15,
      "change": -123.85,
      "change_pct": -6.64,
      "volume_today": 644900,
      "volume_yesterday": 438200,
      "volume_ratio": 47.2,
      "name": "",
      "sector": "",
      "sector_en": "",
      "industry": "",
      "industry_ja": "",
      "description": null,
      "description_ja": "",
      "website": null,
      "chart": null
    },
    {
      "symbol": "NEE",
      "price": 88.34,
      "prev_close": 86.37,
      "change": 1.97,
      "change_pct": 2.28,
      "volume_today": 14281800,
      "volume_yesterday": 9709200,
      "volume_ratio": 47.1,
      "name": "",
      "sector": "",
      "sector_en": "",
      "industry": "",
      "industry_ja": "",
      "description": null,
      "description_ja": "",
      "website": null,
      "chart": null
    },
    {
      "symbol": "FLEX",
      "price": 136.86,
      "prev_close": 153.53,
      "change": -16.67,
      "change_pct": -10.86,
      "volume_today": 6566100,
      "volume_yesterday": 4560000,
      "volume_ratio": 44.0,
      "name": "",
      "sector": "",
      "sector_en": "",
      "industry": "",
      "industry_ja": "",
      "description": null,
      "description_ja": "",
      "website": null,
      "chart": null
    },
    {
      "symbol": "LDOS",
      "price": 108.84,
      "prev_close": 103.07,
      "change": 5.77,
      "change_pct": 5.6,
      "volume_today": 2315500,
      "volume_yesterday": 1645100,
      "volume_ratio": 40.8,
      "name": "",
      "sector": "",
      "sector_en": "",
      "industry": "",
      "industry_ja": "",
      "description": null,
      "description_ja": "",
      "website": null,
      "chart": null
    }
  ]
}