{
  "updated_at": "2026-07-14T22:32:02.478535+00:00",
  "jp_count": 0,
  "us_count": 20,
  "jp_stocks": [],
  "us_stocks": [
    {
      "symbol": "ISRG",
      "price": 379.5,
      "prev_close": 407.12,
      "change": -27.62,
      "change_pct": -6.78,
      "volume_today": 5668144,
      "volume_yesterday": 1801600,
      "volume_ratio": 214.6,
      "name": "",
      "sector": "",
      "sector_en": "",
      "industry": "",
      "industry_ja": "",
      "description": null,
      "description_ja": "",
      "website": null,
      "chart": null
    },
    {
      "symbol": "FE",
      "price": 49.23,
      "prev_close": 48.43,
      "change": 0.8,
      "change_pct": 1.65,
      "volume_today": 6214998,
      "volume_yesterday": 2461500,
      "volume_ratio": 152.5,
      "name": "",
      "sector": "",
      "sector_en": "",
      "industry": "",
      "industry_ja": "",
      "description": null,
      "description_ja": "",
      "website": null,
      "chart": null
    },
    {
      "symbol": "DLR",
      "price": 173.11,
      "prev_close": 177.92,
      "change": -4.81,
      "change_pct": -2.7,
      "volume_today": 3530901,
      "volume_yesterday": 1584600,
      "volume_ratio": 122.8,
      "name": "",
      "sector": "",
      "sector_en": "",
      "industry": "",
      "industry_ja": "",
      "description": null,
      "description_ja": "",
      "website": null,
      "chart": null
    },
    {
      "symbol": "C",
      "price": 133.27,
      "prev_close": 140.71,
      "change": -7.44,
      "change_pct": -5.29,
      "volume_today": 25722587,
      "volume_yesterday": 12439900,
      "volume_ratio": 106.8,
      "name": "",
      "sector": "",
      "sector_en": "",
      "industry": "",
      "industry_ja": "",
      "description": null,
      "description_ja": "",
      "website": null,
      "chart": null
    },
    {
      "symbol": "YUM",
      "price": 158.18,
      "prev_close": 161.68,
      "change": -3.5,
      "change_pct": -2.16,
      "volume_today": 4072899,
      "volume_yesterday": 2222600,
      "volume_ratio": 83.2,
      "name": "",
      "sector": "",
      "sector_en": "",
      "industry": "",
      "industry_ja": "",
      "description": null,
      "description_ja": "",
      "website": null,
      "chart": null
    },
    {
      "symbol": "EBAY",
      "price": 112.54,
      "prev_close": 115.09,
      "change": -2.55,
      "change_pct": -2.22,
      "volume_today": 4282407,
      "volume_yesterday": 2393800,
      "volume_ratio": 78.9,
      "name": "",
      "sector": "",
      "sector_en": "",
      "industry": "",
      "industry_ja": "",
      "description": null,
      "description_ja": "",
      "website": null,
      "chart": null
    },
    {
      "symbol": "BAC",
      "price": 60.62,
      "prev_close": 59.5,
      "change": 1.12,
      "change_pct": 1.88,
      "volume_today": 49159846,
      "volume_yesterday": 27837800,
      "volume_ratio": 76.6,
      "name": "",
      "sector": "",
      "sector_en": "",
      "industry": "",
      "industry_ja": "",
      "description": null,
      "description_ja": "",
      "website": null,
      "chart": null
    },
    {
      "symbol": "ELV",
      "price": 426.79,
      "prev_close": 425.17,
      "change": 1.62,
      "change_pct": 0.38,
      "volume_today": 2192160,
      "volume_yesterday": 1244800,
      "volume_ratio": 76.1,
      "name": "",
      "sector": "",
      "sector_en": "",
      "industry": "",
      "industry_ja": "",
      "description": null,
      "description_ja": "",
      "website": null,
      "chart": null
    },
    {
      "symbol": "MRK",
      "price": 120.78,
      "prev_close": 124.03,
      "change": -3.25,
      "change_pct": -2.62,
      "volume_today": 9082133,
      "volume_yesterday": 5225800,
      "volume_ratio": 73.8,
      "name": "",
      "sector": "",
      "sector_en": "",
      "industry": "",
      "industry_ja": "",
      "description": null,
      "description_ja": "",
      "website": null,
      "chart": null
    },
    {
      "symbol": "GE",
      "price": 353.73,
      "prev_close": 353.42,
      "change": 0.31,
      "change_pct": 0.09,
      "volume_today": 4412325,
      "volume_yesterday": 2668900,
      "volume_ratio": 65.3,
      "name": "",
      "sector": "",
      "sector_en": "",
      "industry": "",
      "industry_ja": "",
      "description": null,
      "description_ja": "",
      "website": null,
      "chart": null
    },
    {
      "symbol": "LH",
      "price": 275.68,
      "prev_close": 276.68,
      "change": -1.0,
      "change_pct": -0.36,
      "volume_today": 651990,
      "volume_yesterday": 396300,
      "volume_ratio": 64.5,
      "name": "",
      "sector": "",
      "sector_en": "",
      "industry": "",
      "industry_ja": "",
      "description": null,
      "description_ja": "",
      "website": null,
      "chart": null
    },
    {
      "symbol": "DELL",
      "price": 457.54,
      "prev_close": 427.11,
      "change": 30.43,
      "change_pct": 7.12,
      "volume_today": 7160327,
      "volume_yesterday": 4661700,
      "volume_ratio": 53.6,
      "name": "",
      "sector": "",
      "sector_en": "",
      "industry": "",
      "industry_ja": "",
      "description": null,
      "description_ja": "",
      "website": null,
      "chart": null
    },
    {
      "symbol": "CTAS",
      "price": 184.33,
      "prev_close": 183.75,
      "change": 0.58,
      "change_pct": 0.32,
      "volume_today": 2938351,
      "volume_yesterday": 1955300,
      "volume_ratio": 50.3,
      "name": "",
      "sector": "",
      "sector_en": "",
      "industry": "",
      "industry_ja": "",
      "description": null,
      "description_ja": "",
      "website": null,
      "chart": null
    },
    {
      "symbol": "IDXX",
      "price": 540.68,
      "prev_close": 564.21,
      "change": -23.53,
      "change_pct": -4.17,
      "volume_today": 779602,
      "volume_yesterday": 522900,
      "volume_ratio": 49.1,
      "name": "",
      "sector": "",
      "sector_en": "",
      "industry": "",
      "industry_ja": "",
      "description": null,
      "description_ja": "",
      "website": null,
      "chart": null
    },
    {
      "symbol": "VST",
      "price": 158.43,
      "prev_close": 158.12,
      "change": 0.31,
      "change_pct": 0.2,
      "volume_today": 5305207,
      "volume_yesterday": 3613300,
      "volume_ratio": 46.8,
      "name": "",
      "sector": "",
      "sector_en": "",
      "industry": "",
      "industry_ja": "",
      "description": null,
      "description_ja": "",
      "website": null,
      "chart": null
    },
    {
      "symbol": "CVNA",
      "price": 70.38,
      "prev_close": 64.99,
      "change": 5.39,
      "change_pct": 8.29,
      "volume_today": 9796126,
      "volume_yesterday": 6705400,
      "volume_ratio": 46.1,
      "name": "",
      "sector": "",
      "sector_en": "",
      "industry": "",
      "industry_ja": "",
      "description": null,
      "description_ja": "",
      "website": null,
      "chart": null
    },
    {
      "symbol": "BF-B",
      "price": 25.1,
      "prev_close": 26.25,
      "change": -1.15,
      "change_pct": -4.38,
      "volume_today": 2823108,
      "volume_yesterday": 1938800,
      "volume_ratio": 45.6,
      "name": "",
      "sector": "",
      "sector_en": "",
      "industry": "",
      "industry_ja": "",
      "description": null,
      "description_ja": "",
      "website": null,
      "chart": null
    },
    {
      "symbol": "NEE",
      "price": 89.54,
      "prev_close": 88.38,
      "change": 1.16,
      "change_pct": 1.31,
      "volume_today": 9760816,
      "volume_yesterday": 6741200,
      "volume_ratio": 44.8,
      "name": "",
      "sector": "",
      "sector_en": "",
      "industry": "",
      "industry_ja": "",
      "description": null,
      "description_ja": "",
      "website": null,
      "chart": null
    },
    {
      "symbol": "LHX",
      "price": 290.01,
      "prev_close": 288.69,
      "change": 1.32,
      "change_pct": 0.46,
      "volume_today": 1033771,
      "volume_yesterday": 722000,
      "volume_ratio": 43.2,
      "name": "",
      "sector": "",
      "sector_en": "",
      "industry": "",
      "industry_ja": "",
      "description": null,
      "description_ja": "",
      "website": null,
      "chart": null
    },
    {
      "symbol": "FFIV",
      "price": 431.26,
      "prev_close": 420.95,
      "change": 10.31,
      "change_pct": 2.45,
      "volume_today": 588495,
      "volume_yesterday": 420200,
      "volume_ratio": 40.1,
      "name": "",
      "sector": "",
      "sector_en": "",
      "industry": "",
      "industry_ja": "",
      "description": null,
      "description_ja": "",
      "website": null,
      "chart": null
    }
  ]
}