{
  "updated_at": "2026-06-08T19:01:48.843757+00:00",
  "jp_count": 0,
  "us_count": 20,
  "jp_stocks": [],
  "us_stocks": [
    {
      "symbol": "TEL",
      "price": 205.65,
      "prev_close": 212.65,
      "change": -7.0,
      "change_pct": -3.29,
      "volume_today": 2497372,
      "volume_yesterday": 1874600,
      "volume_ratio": 33.2,
      "name": "",
      "sector": "",
      "sector_en": "",
      "industry": "",
      "industry_ja": "",
      "description": null,
      "description_ja": "",
      "website": null,
      "chart": null
    },
    {
      "symbol": "AZO",
      "price": 3081.12,
      "prev_close": 3116.43,
      "change": -35.31,
      "change_pct": -1.13,
      "volume_today": 540266,
      "volume_yesterday": 408000,
      "volume_ratio": 32.4,
      "name": "",
      "sector": "",
      "sector_en": "",
      "industry": "",
      "industry_ja": "",
      "description": null,
      "description_ja": "",
      "website": null,
      "chart": null
    },
    {
      "symbol": "CNC",
      "price": 64.78,
      "prev_close": 62.33,
      "change": 2.45,
      "change_pct": 3.93,
      "volume_today": 4234392,
      "volume_yesterday": 3961000,
      "volume_ratio": 6.9,
      "name": "",
      "sector": "",
      "sector_en": "",
      "industry": "",
      "industry_ja": "",
      "description": null,
      "description_ja": "",
      "website": null,
      "chart": null
    },
    {
      "symbol": "XEL",
      "price": 77.48,
      "prev_close": 79.04,
      "change": -1.56,
      "change_pct": -1.97,
      "volume_today": 5454206,
      "volume_yesterday": 5334100,
      "volume_ratio": 2.3,
      "name": "",
      "sector": "",
      "sector_en": "",
      "industry": "",
      "industry_ja": "",
      "description": null,
      "description_ja": "",
      "website": null,
      "chart": null
    },
    {
      "symbol": "PAYX",
      "price": 99.56,
      "prev_close": 100.53,
      "change": -0.97,
      "change_pct": -0.96,
      "volume_today": 2239595,
      "volume_yesterday": 2410100,
      "volume_ratio": -7.1,
      "name": "",
      "sector": "",
      "sector_en": "",
      "industry": "",
      "industry_ja": "",
      "description": null,
      "description_ja": "",
      "website": null,
      "chart": null
    },
    {
      "symbol": "BXP",
      "price": 64.54,
      "prev_close": 62.33,
      "change": 2.21,
      "change_pct": 3.55,
      "volume_today": 1178904,
      "volume_yesterday": 1306400,
      "volume_ratio": -9.8,
      "name": "",
      "sector": "",
      "sector_en": "",
      "industry": "",
      "industry_ja": "",
      "description": null,
      "description_ja": "",
      "website": null,
      "chart": null
    },
    {
      "symbol": "FIS",
      "price": 39.79,
      "prev_close": 40.95,
      "change": -1.16,
      "change_pct": -2.83,
      "volume_today": 4037254,
      "volume_yesterday": 4683400,
      "volume_ratio": -13.8,
      "name": "",
      "sector": "",
      "sector_en": "",
      "industry": "",
      "industry_ja": "",
      "description": null,
      "description_ja": "",
      "website": null,
      "chart": null
    },
    {
      "symbol": "HSY",
      "price": 175.61,
      "prev_close": 184.58,
      "change": -8.97,
      "change_pct": -4.86,
      "volume_today": 1368780,
      "volume_yesterday": 1618300,
      "volume_ratio": -15.4,
      "name": "",
      "sector": "",
      "sector_en": "",
      "industry": "",
      "industry_ja": "",
      "description": null,
      "description_ja": "",
      "website": null,
      "chart": null
    },
    {
      "symbol": "PTC",
      "price": 136.99,
      "prev_close": 137.0,
      "change": -0.01,
      "change_pct": -0.0,
      "volume_today": 939670,
      "volume_yesterday": 1111200,
      "volume_ratio": -15.4,
      "name": "",
      "sector": "",
      "sector_en": "",
      "industry": "",
      "industry_ja": "",
      "description": null,
      "description_ja": "",
      "website": null,
      "chart": null
    },
    {
      "symbol": "ALGN",
      "price": 172.3,
      "prev_close": 167.74,
      "change": 4.56,
      "change_pct": 2.72,
      "volume_today": 415253,
      "volume_yesterday": 494400,
      "volume_ratio": -16.0,
      "name": "",
      "sector": "",
      "sector_en": "",
      "industry": "",
      "industry_ja": "",
      "description": null,
      "description_ja": "",
      "website": null,
      "chart": null
    },
    {
      "symbol": "SATS",
      "price": 115.22,
      "prev_close": 116.28,
      "change": -1.06,
      "change_pct": -0.91,
      "volume_today": 8020934,
      "volume_yesterday": 9720600,
      "volume_ratio": -17.5,
      "name": "",
      "sector": "",
      "sector_en": "",
      "industry": "",
      "industry_ja": "",
      "description": null,
      "description_ja": "",
      "website": null,
      "chart": null
    },
    {
      "symbol": "TDY",
      "price": 610.94,
      "prev_close": 602.27,
      "change": 8.67,
      "change_pct": 1.44,
      "volume_today": 183268,
      "volume_yesterday": 222200,
      "volume_ratio": -17.5,
      "name": "",
      "sector": "",
      "sector_en": "",
      "industry": "",
      "industry_ja": "",
      "description": null,
      "description_ja": "",
      "website": null,
      "chart": null
    },
    {
      "symbol": "AAPL",
      "price": 303.73,
      "prev_close": 307.34,
      "change": -3.61,
      "change_pct": -1.18,
      "volume_today": 51749230,
      "volume_yesterday": 65246700,
      "volume_ratio": -20.7,
      "name": "",
      "sector": "",
      "sector_en": "",
      "industry": "",
      "industry_ja": "",
      "description": null,
      "description_ja": "",
      "website": null,
      "chart": null
    },
    {
      "symbol": "TAP",
      "price": 39.72,
      "prev_close": 39.06,
      "change": 0.66,
      "change_pct": 1.69,
      "volume_today": 2083258,
      "volume_yesterday": 2714300,
      "volume_ratio": -23.2,
      "name": "",
      "sector": "",
      "sector_en": "",
      "industry": "",
      "industry_ja": "",
      "description": null,
      "description_ja": "",
      "website": null,
      "chart": null
    },
    {
      "symbol": "PFE",
      "price": 25.65,
      "prev_close": 26.04,
      "change": -0.4,
      "change_pct": -1.52,
      "volume_today": 24588894,
      "volume_yesterday": 32159700,
      "volume_ratio": -23.5,
      "name": "",
      "sector": "",
      "sector_en": "",
      "industry": "",
      "industry_ja": "",
      "description": null,
      "description_ja": "",
      "website": null,
      "chart": null
    },
    {
      "symbol": "INTC",
      "price": 111.52,
      "prev_close": 99.17,
      "change": 12.35,
      "change_pct": 12.45,
      "volume_today": 107910145,
      "volume_yesterday": 144388800,
      "volume_ratio": -25.3,
      "name": "",
      "sector": "",
      "sector_en": "",
      "industry": "",
      "industry_ja": "",
      "description": null,
      "description_ja": "",
      "website": null,
      "chart": null
    },
    {
      "symbol": "TRMB",
      "price": 53.93,
      "prev_close": 54.19,
      "change": -0.26,
      "change_pct": -0.48,
      "volume_today": 1745711,
      "volume_yesterday": 2362900,
      "volume_ratio": -26.1,
      "name": "",
      "sector": "",
      "sector_en": "",
      "industry": "",
      "industry_ja": "",
      "description": null,
      "description_ja": "",
      "website": null,
      "chart": null
    },
    {
      "symbol": "AVB",
      "price": 187.2,
      "prev_close": 189.72,
      "change": -2.52,
      "change_pct": -1.33,
      "volume_today": 640858,
      "volume_yesterday": 874700,
      "volume_ratio": -26.7,
      "name": "",
      "sector": "",
      "sector_en": "",
      "industry": "",
      "industry_ja": "",
      "description": null,
      "description_ja": "",
      "website": null,
      "chart": null
    },
    {
      "symbol": "CRL",
      "price": 184.6,
      "prev_close": 181.34,
      "change": 3.26,
      "change_pct": 1.8,
      "volume_today": 374093,
      "volume_yesterday": 519300,
      "volume_ratio": -28.0,
      "name": "",
      "sector": "",
      "sector_en": "",
      "industry": "",
      "industry_ja": "",
      "description": null,
      "description_ja": "",
      "website": null,
      "chart": null
    },
    {
      "symbol": "LLY",
      "price": 1156.56,
      "prev_close": 1131.42,
      "change": 25.14,
      "change_pct": 2.22,
      "volume_today": 2930585,
      "volume_yesterday": 4120400,
      "volume_ratio": -28.9,
      "name": "",
      "sector": "",
      "sector_en": "",
      "industry": "",
      "industry_ja": "",
      "description": null,
      "description_ja": "",
      "website": null,
      "chart": null
    }
  ]
}